gitfighters/__init__.py
gitfighters/benchmark.py
gitfighters/git_fighters.py
gitfighters/latex.py
gitfighters/parse.py
gitfighters/parsing.py
gitfighters/vector.py
gitfighters/visualize.py
tests/__init__.py
tests/test_AD.py
tests/test_fightingAD.py
fightingAD-0.0.1.dist-info/LICENSE
fightingAD-0.0.1.dist-info/METADATA
fightingAD-0.0.1.dist-info/WHEEL
fightingAD-0.0.1.dist-info/top_level.txt
fightingAD-0.0.1.dist-info/RECORD
